samil/__init__.py
samil/cli.py
samil/influx.py
samil/inverter.py
samil/inverterutil.py
samil/pvoutput.py
samil/statustypes.py
samil-2.3.dist-info/LICENSE
samil-2.3.dist-info/METADATA
samil-2.3.dist-info/WHEEL
samil-2.3.dist-info/entry_points.txt
samil-2.3.dist-info/top_level.txt
samil-2.3.dist-info/RECORD
