Metadata-Version: 2.2
Name: samil
Version: 2.3
Summary: Samil Power inverter tool
Home-page: https://github.com/mhvis/solar
Author: Maarten Visscher
Author-email: mail@maartenvisscher.nl
Classifier: Programming Language :: Python :: 3
Classifier: License :: OSI Approved :: MIT License
Classifier: Operating System :: OS Independent
Requires-Python: >=3.8
License-File: LICENSE
Requires-Dist: paho-mqtt<2,>=1.5.0
Requires-Dist: click<9,>=7.1.2
Requires-Dist: influxdb-client<2,>=1.32.0
Dynamic: author
Dynamic: author-email
Dynamic: classifier
Dynamic: description
Dynamic: description-content-type
Dynamic: home-page
Dynamic: requires-dist
Dynamic: requires-python
Dynamic: summary
